dcapi/__init__.py
dcapi/dcapi.py
dcapi-0.0.5.dist-info/DESCRIPTION.rst
dcapi-0.0.5.dist-info/METADATA
dcapi-0.0.5.dist-info/RECORD
dcapi-0.0.5.dist-info/WHEEL
dcapi-0.0.5.dist-info/metadata.json
dcapi-0.0.5.dist-info/top_level.txt
