Metadata-Version: 2.0
Name: dcapi
Version: 0.0.5
Summary: Wrapper for dcapi
Home-page: https://github.com/lethargilistic/dcapi-wrap
Author: Mike Overby
Author-email: mikeoverby@outlook.com
License: MIT
Keywords: api
Platform: UNKNOWN
Classifier: Intended Audience :: Developers
Classifier: License :: OSI Approved :: MIT License
Classifier: Natural Language :: English
Classifier: Programming Language :: Python
Classifier: Programming Language :: Python :: 3
Classifier: Programming Language :: Python :: 3.5
Requires-Dist: requests (==2.17.3)
Requires-Dist: wheel (==0.29.0)
